baykeshop/__init__.py
baykeshop/py.typed
baykeshop/urls.py
baykeshop/api/__init__.py
baykeshop/api/urls.py
baykeshop/api/carts/__init__.py
baykeshop/api/carts/serializers.py
baykeshop/api/carts/views.py
baykeshop/api/comments/__init__.py
baykeshop/api/comments/serializers.py
baykeshop/api/comments/views.py
baykeshop/api/orders/__init__.py
baykeshop/api/orders/serializers.py
baykeshop/api/orders/views.py
baykeshop/api/pay/__init__.py
baykeshop/api/pay/serializers.py
baykeshop/api/pay/views.py
baykeshop/api/upload/serializers.py
baykeshop/api/upload/views.py
baykeshop/conf/__init__.py
baykeshop/conf/defaults.py
baykeshop/conf/settings.py
baykeshop/contrib/__init__.py
baykeshop/contrib/article/__init__.py
baykeshop/contrib/article/admin.py
baykeshop/contrib/article/apps.py
baykeshop/contrib/article/models.py
baykeshop/contrib/article/tests.py
baykeshop/contrib/article/urls.py
baykeshop/contrib/article/views.py
baykeshop/contrib/article/migrations/0001_initial.py
baykeshop/contrib/article/migrations/__init__.py
baykeshop/contrib/article/templates/baykeshop/article/archive.html
baykeshop/contrib/article/templates/baykeshop/article/base.html
baykeshop/contrib/article/templates/baykeshop/article/detail.html
baykeshop/contrib/article/templates/baykeshop/article/list.html
baykeshop/contrib/article/templates/baykeshop/sidebar/archive.html
baykeshop/contrib/article/templates/baykeshop/sidebar/custom.html
baykeshop/contrib/article/templates/baykeshop/sidebar/nav.html
baykeshop/contrib/article/templates/baykeshop/sidebar/search.html
baykeshop/contrib/article/templates/baykeshop/sidebar/tags.html
baykeshop/contrib/article/templatetags/__init__.py
baykeshop/contrib/article/templatetags/baykearticle.py
baykeshop/contrib/member/__init__.py
baykeshop/contrib/member/admin.py
baykeshop/contrib/member/apps.py
baykeshop/contrib/member/models.py
baykeshop/contrib/member/tests.py
baykeshop/contrib/member/urls.py
baykeshop/contrib/member/forms/__init__.py
baykeshop-1.3.25.dist-info/METADATA
baykeshop-1.3.25.dist-info/WHEEL
baykeshop-1.3.25.dist-info/licenses/LICENSE
baykeshop-1.3.25.dist-info/RECORD
