Metadata-Version: 2.4
Name: baykeshop
Version: 1.3.25
Summary: BaykeShop开源商城系统，基于django框架！
Project-URL: Homepage, https://gitee.com/xingfugz/bayke-shop
Project-URL: Bug Tracker, https://gitee.com/xingfugz/bayke-shop/issues
Project-URL: Documentation, https://gitee.com/xingfugz/bayke-shop
Project-URL: Source Code, https://github.com/xingfuggz/baykeShop
Author-email: 轻编程 <2539909370@qq.com>
License: GPL-2.0
License-File: LICENSE
Requires-Python: >=3.11.10
Requires-Dist: alipay-sdk-python>=3.7.345
Requires-Dist: django==4.2.17
Requires-Dist: djangorestframework>=3.15.2
Requires-Dist: pillow>=11.0.0
Requires-Dist: pyecharts>=2.0.7
